MANIFEST.in
README.md
samira9a7ba.py
setup.py
samira97ba.egg-info/PKG-INFO
samira97ba.egg-info/SOURCES.txt
samira97ba.egg-info/dependency_links.txt
samira97ba.egg-info/top_level.txt