Metadata-Version: 2.1
Name: samira97ba
Version: 0.1
Summary: A package that calculates surface of geometric shapes
Author: Belajdel rabek 
Author-email: belajdelmedamine@gmail.com
